llm2geneset/__init__.py
llm2geneset/llm2geneset.py
llm2geneset/skeleton.py
llm2geneset/stats.py
llm2geneset/prompts/genes_concise.txt
llm2geneset/prompts/genes_concise_conf.txt
llm2geneset/prompts/genes_concise_reason.txt
llm2geneset/prompts/gsai_prompt.txt
llm2geneset/prompts/pathways_from_genes.txt
llm2geneset/prompts/pathways_from_genes_context.txt
llm2geneset-0.0.6.dist-info/LICENSE.txt
llm2geneset-0.0.6.dist-info/METADATA
llm2geneset-0.0.6.dist-info/WHEEL
llm2geneset-0.0.6.dist-info/top_level.txt
llm2geneset-0.0.6.dist-info/RECORD
