Metadata-Version: 2.2
Name: llm2geneset
Version: 0.0.6
Summary: llm2geneset
Home-page: https://github.com/Alector-BIO/llm2geneset
Author: Zia Khan
Author-email: zia.khan@alector.com
License: MIT
Platform: any
Classifier: Development Status :: 4 - Beta
Classifier: Programming Language :: Python :: 3
Classifier: License :: OSI Approved :: MIT License
Classifier: Operating System :: OS Independent
License-File: LICENSE.txt
Requires-Dist: importlib-metadata; python_version < "3.8"
Requires-Dist: pandas<3,>=2.2.3
Requires-Dist: tqdm<5,>=4.66.5
Requires-Dist: scipy<2,>=1.14.1
Requires-Dist: statsmodels<0.15,>=0.14.4
Requires-Dist: aiohttp<4,>=3.10.10
Requires-Dist: openai<2,>=1.51.2
Requires-Dist: json_repair
Requires-Dist: asynciolimiter
Provides-Extra: testing
Requires-Dist: setuptools; extra == "testing"
Requires-Dist: pytest; extra == "testing"
Requires-Dist: pytest-cov; extra == "testing"
